case_class/__init__.py
case_class/case_class.py
case_class/clsutils.py
case_class/exceptions.py
case_class/signature.py
case_class/utils.py
case_class-0.0.8.dist-info/DESCRIPTION.rst
case_class-0.0.8.dist-info/METADATA
case_class-0.0.8.dist-info/RECORD
case_class-0.0.8.dist-info/WHEEL
case_class-0.0.8.dist-info/metadata.json
case_class-0.0.8.dist-info/top_level.txt
