Metadata-Version: 2.0
Name: case-class
Version: 0.0.8
Summary: Scala-like CaseClasses for Python
Home-page: https://github.com/tkw1536/PythonCaseClass
Author: Tom Wiesing
Author-email: tkw01536@gmail.com
License: MIT
Platform: UNKNOWN
Classifier: Programming Language :: Python :: 2
Classifier: Programming Language :: Python :: 3
Classifier: License :: OSI Approved :: MIT License
Classifier: Topic :: Software Development :: Libraries
Classifier: Intended Audience :: Developers
Classifier: Topic :: Utilities
